Metadata-Version: 2.1
Name: tchotchke
Version: 0.1.16
Summary: Trinkets and baubles to adorn your pythonic pursuits.
Home-page: https://github.com/josiahdc/tchotchke
Author: Josiah Chapman
Author-email: josiah.chapman@gmail.com
License: UNKNOWN
Platform: UNKNOWN
License-File: LICENSE
